put_main.py
put_main-1.0.dist-info/WHEEL
put_main-1.0.dist-info/METADATA
put_main-1.0.dist-info/RECORD
