Metadata-Version: 2.1
Name: put-main
Version: 1.0
Summary: A set of utility classes and functions
Author: Roberto Amadori
Requires-Python: >=3.9,<4.0
Classifier: Programming Language :: Python :: 3
Classifier: Programming Language :: Python :: 3.9
